README.md
setup.py
moonshotai_integration/data_integration.py
moonshotai_integration.egg-info/PKG-INFO
moonshotai_integration.egg-info/SOURCES.txt
moonshotai_integration.egg-info/dependency_links.txt
moonshotai_integration.egg-info/not-zip-safe
moonshotai_integration.egg-info/requires.txt
moonshotai_integration.egg-info/top_level.txt
moonshotai_integration/utils/consts.py
moonshotai_integration/utils/exceptions.py
moonshotai_integration/utils/response.py
moonshotai_integration/utils/utils.py