Metadata-Version: 1.0
Name: moonshotai-integration
Version: 0.0.2
Summary: MoonshotAI Data Integration SDK
Home-page: UNKNOWN
Author: Tomer Efr
Author-email: UNKNOWN
License: MIT
Platform: UNKNOWN
